halcyon/__init__.py
halcyon/__main__.py
halcyon/enums.py
halcyon/halcyon.py
halcyon/message.py
halcyon/restrunner.py
halcyon/room.py
halcyon/security.py
halcyon-1.3.0.dist-info/licenses/LICENSE
halcyon-1.3.0.dist-info/METADATA
halcyon-1.3.0.dist-info/WHEEL
halcyon-1.3.0.dist-info/top_level.txt
halcyon-1.3.0.dist-info/RECORD
