Metadata-Version: 2.4
Name: halcyon
Version: 1.3.0
Summary: Halcyon is an easy to use matrix library
Home-page: https://github.com/WesR/Halcyon
Author: Wes Ring
Author-email: hello@wesring.com
License: BSD 3-Clause License
Project-URL: Bug Tracker, https://github.com/WesR/Halcyon/issues
Classifier: Programming Language :: Python :: 3
Classifier: License :: OSI Approved :: BSD License
Classifier: Operating System :: OS Independent
Classifier: Topic :: Utilities
Classifier: Topic :: Software Development :: Libraries
Requires-Python: >=3.7
License-File: LICENSE
Requires-Dist: requests
Requires-Dist: aiohttp>=3.8.0
Requires-Dist: markdown
Requires-Dist: Pillow
Requires-Dist: blurhash-python
Requires-Dist: pydantic>=2.0.0
Provides-Extra: dev
Requires-Dist: pytest>=7.0.0; extra == "dev"
Requires-Dist: pytest-cov>=3.0.0; extra == "dev"
Requires-Dist: pytest-asyncio>=0.21.0; extra == "dev"
Dynamic: license-file
